{"姚合":{"author":"姚合","authordesc":"合陜州人崇之玄孫以詩聞元和十一年第進士歴武功主簿富平萬年尉寶歴中監察殿中御史戸部貟外郎歴金杭二州刺史爲刑户二部郎中諫議大夫給事中陜虢觀察使開成末終秘書監合世號以詩名重於時人稱其起家舊閥閲號姚武功云\n紀事云合與馬戴費冠卿殷堯藩張籍遊李頻師之合有極玄集取王維等二十六人詩百篇曰此詩中射雕手也","charstyleMap":{"古體詩":[{"id":64019,"title":"莊居野行","titledesc":"","poemindex":1},{"id":64020,"title":"新昌里","titledesc":"","poemindex":2},{"id":64021,"title":"過張邯鄲莊","titledesc":"","poemindex":3},{"id":64022,"title":"答竇知言","titledesc":"","poemindex":4},{"id":64023,"title":"寄狄拾遺時魏州從事","titledesc":"","poemindex":5},{"id":64024,"title":"秋中寄崔道士","titledesc":"","poemindex":6},{"id":64025,"title":"送張宗原","titledesc":"","poemindex":7},{"id":64026,"title":"送王求","titledesc":"","poemindex":8}],"近體詩":[{"id":64027,"title":"閒居遣懷","titledesc":"","poemindex":9},{"id":64028,"title":"閒居遣懷","titledesc":"","poemindex":10},{"id":64029,"title":"閒居遣懷","titledesc":"","poemindex":11},{"id":64030,"title":"閒居遣懷","titledesc":"","poemindex":12},{"id":64031,"title":"閒居遣懷","titledesc":"","poemindex":13},{"id":64032,"title":"原上新居〈一作王建詩〉","titledesc":"","poemindex":14},{"id":64033,"title":"秋日閒居","titledesc":"","poemindex":15},{"id":64034,"title":"山村","titledesc":"","poemindex":16},{"id":64035,"title":"閒居遣興","titledesc":"","poemindex":17},{"id":64036,"title":"閒居","titledesc":"","poemindex":18},{"id":64037,"title":"遊春","titledesc":"","poemindex":19},{"id":64038,"title":"遊春","titledesc":"","poemindex":20},{"id":64039,"title":"遊春","titledesc":"","poemindex":21},{"id":64040,"title":"遊春","titledesc":"","poemindex":22},{"id":64041,"title":"遊春","titledesc":"","poemindex":23},{"id":64042,"title":"秋日有懷","titledesc":"","poemindex":24},{"id":64043,"title":"同衛尉崔少卿九月六日飲","titledesc":"","poemindex":25},{"id":64044,"title":"客遊旅懷","titledesc":"","poemindex":26},{"id":64045,"title":"夏日登樓晚望","titledesc":"","poemindex":27},{"id":64046,"title":"武功縣中作","titledesc":"","poemindex":28},{"id":64047,"title":"武功縣中作","titledesc":"","poemindex":29},{"id":64048,"title":"武功縣中作","titledesc":"","poemindex":30},{"id":64049,"title":"武功縣中作","titledesc":"","poemindex":31},{"id":64050,"title":"武功縣中作","titledesc":"","poemindex":32},{"id":64051,"title":"武功縣中作","titledesc":"","poemindex":33},{"id":64052,"title":"武功縣中作","titledesc":"","poemindex":34},{"id":64053,"title":"武功縣中作","titledesc":"","poemindex":35},{"id":64054,"title":"武功縣中作","titledesc":"","poemindex":36},{"id":64055,"title":"武功縣中作","titledesc":"","poemindex":37},{"id":64056,"title":"武功縣中作","titledesc":"","poemindex":38},{"id":64057,"title":"武功縣中作","titledesc":"","poemindex":39},{"id":64058,"title":"武功縣中作","titledesc":"","poemindex":40},{"id":64059,"title":"武功縣中作","titledesc":"","poemindex":41},{"id":64060,"title":"武功縣中作","titledesc":"","poemindex":42},{"id":64061,"title":"武功縣中作","titledesc":"","poemindex":43},{"id":64062,"title":"武功縣中作","titledesc":"","poemindex":44},{"id":64063,"title":"武功縣中作","titledesc":"","poemindex":45},{"id":64064,"title":"武功縣中作","titledesc":"","poemindex":46},{"id":64065,"title":"武功縣中作","titledesc":"","poemindex":47},{"id":64066,"title":"武功縣中作","titledesc":"","poemindex":48},{"id":64067,"title":"武功縣中作","titledesc":"","poemindex":49},{"id":64068,"title":"武功縣中作","titledesc":"","poemindex":50},{"id":64069,"title":"武功縣中作","titledesc":"","poemindex":51},{"id":64070,"title":"武功縣中作","titledesc":"","poemindex":52},{"id":64071,"title":"武功縣中作","titledesc":"","poemindex":53},{"id":64072,"title":"武功縣中作","titledesc":"","poemindex":54},{"id":64073,"title":"揚州春詞","titledesc":"","poemindex":55},{"id":64074,"title":"揚州春詞","titledesc":"","poemindex":56},{"id":64075,"title":"題杭州南亭","titledesc":"","poemindex":57},{"id":64076,"title":"喜馬戴冬夜見過期無可不至","titledesc":"","poemindex":58},{"id":64077,"title":"贈劉叉","titledesc":"","poemindex":59},{"id":64078,"title":"春日早朝寄劉起居","titledesc":"","poemindex":60},{"id":64079,"title":"寄主客劉員外〈禹錫〉","titledesc":"","poemindex":61},{"id":64080,"title":"秋日寄李支使","titledesc":"","poemindex":62},{"id":64081,"title":"寄陸渾縣尉李景先","titledesc":"","poemindex":63},{"id":64082,"title":"寄賈島","titledesc":"","poemindex":64},{"id":64083,"title":"寄無可上人","titledesc":"","poemindex":65},{"id":64084,"title":"寄賈島","titledesc":"","poemindex":66},{"id":64085,"title":"寄不出院僧","titledesc":"","poemindex":67},{"id":64086,"title":"别賈島","titledesc":"","poemindex":68},{"id":64087,"title":"送右司薛貟外赴處州","titledesc":"","poemindex":69},{"id":64088,"title":"送崔中丞赴鄭州","titledesc":"","poemindex":70},{"id":64089,"title":"送殷堯藩侍御遊山南","titledesc":"","poemindex":71},{"id":64090,"title":"送裴宰君","titledesc":"","poemindex":72},{"id":64091,"title":"送潘傳秀才歸宣州","titledesc":"","poemindex":73},{"id":64092,"title":"送李傅秀才歸宣州","titledesc":"","poemindex":74},{"id":64093,"title":"送雍陶游蜀","titledesc":"","poemindex":75},{"id":64094,"title":"送崔之仁〈一作别劉徳仁〉","titledesc":"","poemindex":76},{"id":64095,"title":"送宋慎言","titledesc":"","poemindex":77},{"id":64096,"title":"送王龜處士","titledesc":"","poemindex":78},{"id":64097,"title":"病中辱朱諫議惠甘菊藥苗因以詩贈","titledesc":"","poemindex":79},{"id":64098,"title":"聞蟬寄賈島","titledesc":"","poemindex":80},{"id":64099,"title":"西掖寓直春曉聞殘漏","titledesc":"","poemindex":81},{"id":64100,"title":"省直書事","titledesc":"","poemindex":82},{"id":64101,"title":"和門下李相餞西蜀相公","titledesc":"","poemindex":83},{"id":64102,"title":"和座主相公西亭秋日即事","titledesc":"","poemindex":84},{"id":64103,"title":"酬任疇協律夏中苦雨見寄","titledesc":"","poemindex":85},{"id":64104,"title":"喜胡遇至","titledesc":"","poemindex":86},{"id":64105,"title":"杭州觀潮","titledesc":"","poemindex":87},{"id":64106,"title":"題鳳翔西郭新亭","titledesc":"","poemindex":88},{"id":64107,"title":"題河上亭","titledesc":"","poemindex":89},{"id":64108,"title":"題山寺","titledesc":"","poemindex":90},{"id":64109,"title":"題宣義池亭","titledesc":"","poemindex":91},{"id":64110,"title":"題鄭〈一作崔〉駙馬林亭","titledesc":"","poemindex":92},{"id":64111,"title":"題長安薛員外水閣","titledesc":"","poemindex":93},{"id":64112,"title":"寄題尉遲少卿郊居","titledesc":"","poemindex":94},{"id":64113,"title":"寄華州李中丞","titledesc":"","poemindex":95},{"id":64114,"title":"金州書事寄山中舊友","titledesc":"","poemindex":96},{"id":64115,"title":"寄王度居士","titledesc":"","poemindex":97},{"id":64116,"title":"病中書事寄友人","titledesc":"","poemindex":98},{"id":64117,"title":"贈張籍太祝","titledesc":"","poemindex":99},{"id":64118,"title":"贈終南山傅山人","titledesc":"","poemindex":100},{"id":64119,"title":"冬夜宴韓卿宅送崔元亮赴果州","titledesc":"","poemindex":101},{"id":64120,"title":"送韓湘赴湖西從事","titledesc":"","poemindex":102},{"id":64121,"title":"送杜立歸蜀","titledesc":"","poemindex":103},{"id":64122,"title":"迎春","titledesc":"","poemindex":104},{"id":64123,"title":"賞春","titledesc":"","poemindex":105},{"id":64124,"title":"别春","titledesc":"","poemindex":106},{"id":64125,"title":"將歸山","titledesc":"","poemindex":107},{"id":64126,"title":"罷武功縣將入城","titledesc":"","poemindex":108},{"id":64127,"title":"罷武功縣將入城","titledesc":"","poemindex":109},{"id":64128,"title":"題田將軍宅","titledesc":"","poemindex":110},{"id":64129,"title":"題崔駙馬宅","titledesc":"","poemindex":111},{"id":64130,"title":"酬薛奉禮見寄","titledesc":"","poemindex":112},{"id":64131,"title":"贈王尊師","titledesc":"","poemindex":113},{"id":64132,"title":"和髙諫議䝉兼賓客時入翰苑","titledesc":"","poemindex":114},{"id":64133,"title":"和劉禹錫主客冬初拜表懷上都故人","titledesc":"","poemindex":115},{"id":64134,"title":"寄東都白賓客居易","titledesc":"","poemindex":116},{"id":64135,"title":"寄崔之仁山人","titledesc":"","poemindex":117},{"id":64136,"title":"送劉禹錫郎中赴蘇州","titledesc":"","poemindex":118},{"id":64137,"title":"送劉禹錫郎中赴蘇州","titledesc":"","poemindex":119},{"id":64138,"title":"送林使君赴邵州","titledesc":"","poemindex":120},{"id":64139,"title":"送獨孤煥評事赴豐州","titledesc":"","poemindex":121},{"id":64140,"title":"送源中丞赴新羅","titledesc":"","poemindex":122},{"id":64141,"title":"别友人山居","titledesc":"","poemindex":123},{"id":64142,"title":"送無可上人游越","titledesc":"","poemindex":124},{"id":64143,"title":"送僧實歸杭州天竺","titledesc":"","poemindex":125},{"id":64144,"title":"咏貴游","titledesc":"","poemindex":126},{"id":64145,"title":"和李裴二舍人兩閣老酬白少傅見寄","titledesc":"","poemindex":127},{"id":64146,"title":"秋中夜坐","titledesc":"","poemindex":128},{"id":64147,"title":"古碑","titledesc":"","poemindex":129},{"id":64148,"title":"楊桺枝詞","titledesc":"","poemindex":130},{"id":64149,"title":"楊桺枝詞","titledesc":"","poemindex":131},{"id":64150,"title":"楊桺枝詞","titledesc":"","poemindex":132},{"id":64151,"title":"楊桺枝詞","titledesc":"","poemindex":133},{"id":64152,"title":"窮邊詞","titledesc":"","poemindex":134},{"id":64153,"title":"游天長寺上方","titledesc":"","poemindex":135},{"id":64154,"title":"夜期賈島不至","titledesc":"","poemindex":136},{"id":64155,"title":"酬令狐郎中見寄","titledesc":"","poemindex":137},{"id":64156,"title":"和前吏部韓侍郎夜泛南溪","titledesc":"","poemindex":138},{"id":64157,"title":"乞新茶","titledesc":"","poemindex":139}]}},"朱慶餘":{"author":"朱慶餘","authordesc":"慶餘名可久以字行越州人受知於張籍登寶厯進士第而官不達\n摭言云慶餘遇籍知音索其篇什數通吟改只留二十六章置懷抱而推贊之時人以籍重名無不繕錄諷詠遂登科第初慶餘尚為謙退作閨意一篇以獻籍籍酬之有一曲敵萬金之句自是詩名流於海内\n張洎云元和中張水部格律不涉舊體惟朱慶餘一人親受其㫖而項斯亦為水部所賞然則韓門諸人詩𣲖分異朱慶餘項斯以下為張籍之𣲖姚合李洞方干而下則賈島之𣲖也","charstyleMap":{"近體詩":[{"id":64158,"title":"泛溪","titledesc":"","poemindex":140},{"id":64159,"title":"鳳翔西池與賈島納凉","titledesc":"","poemindex":141},{"id":64160,"title":"與石畫秀才過普照寺","titledesc":"","poemindex":142},{"id":64161,"title":"望蕭關","titledesc":"","poemindex":143},{"id":64162,"title":"和劉補闕秋園寓興之什","titledesc":"","poemindex":144},{"id":64163,"title":"和劉補闕秋園寓興之什","titledesc":"","poemindex":145},{"id":64164,"title":"和劉補闕秋園寓興之什","titledesc":"","poemindex":146},{"id":64165,"title":"和劉補闕秋園寓興之什","titledesc":"","poemindex":147},{"id":64166,"title":"和劉補闕秋園寓興之什","titledesc":"","poemindex":148},{"id":64167,"title":"和劉補闕秋園寓興之什","titledesc":"","poemindex":149},{"id":64168,"title":"和劉補闕秋園寓興之什","titledesc":"","poemindex":150},{"id":64169,"title":"和劉補闕秋園寓興之什","titledesc":"","poemindex":151},{"id":64170,"title":"和劉補闕秋園寓興之什","titledesc":"","poemindex":152},{"id":64171,"title":"和劉補闕秋園寓興之什","titledesc":"","poemindex":153},{"id":64172,"title":"上張水部","titledesc":"","poemindex":154},{"id":64173,"title":"夏末留别洞庭知已","titledesc":"","poemindex":155},{"id":64174,"title":"題薔薇花","titledesc":"","poemindex":156},{"id":64175,"title":"歸故園","titledesc":"","poemindex":157},{"id":64176,"title":"南湖","titledesc":"","poemindex":158},{"id":64177,"title":"與龎復言擕酒望洞庭","titledesc":"","poemindex":159},{"id":64178,"title":"題章正字道正新居","titledesc":"","poemindex":160},{"id":64179,"title":"題王丘長史宅","titledesc":"","poemindex":161},{"id":64180,"title":"題錢宇别墅","titledesc":"","poemindex":162},{"id":64181,"title":"贈韓協律","titledesc":"","poemindex":163},{"id":64182,"title":"過舊宅","titledesc":"","poemindex":164},{"id":64183,"title":"宫詞","titledesc":"","poemindex":165},{"id":64184,"title":"公子行","titledesc":"","poemindex":166},{"id":64185,"title":"近試上張水部閨意","titledesc":"","poemindex":167}]}}}