[
  {
    "id": 58895,
    "uid": "poem-17-4",
    "chapter": "卷十七",
    "chapternum": 17,
    "charstyle": "古體詩",
    "title": "牧童詞",
    "titledesc": "",
    "collection": "",
    "collectiondesc": "",
    "poemindex": 4,
    "author": "儲光羲",
    "content": "不言牧田逺不道牧陂深所念牛馴擾不亂牧童心圓笠覆我首長蓑披我襟方將憂暑雨亦以懼寒陰大牛隱層坂小牛穿近林同類相鼓舞觸物成謳吟取樂須㬰間寧問聲與音"
  },
  {
    "id": 58905,
    "uid": "poem-17-14",
    "chapter": "卷十七",
    "chapternum": 17,
    "charstyle": "古體詩",
    "title": "使過彈箏峽作",
    "titledesc": "",
    "collection": "",
    "collectiondesc": "",
    "poemindex": 14,
    "author": "儲光羲",
    "content": "烏雀知天雪羣飛復羣鳴原田無遺粟日暮滿空城達士憂世務鄙夫念王程晨過彈箏峽馬足凌兢行雙壁隱靈曜莫能知晦明皚皚堅氷白漫漫陰雲平始信古人言苦節不可貞"
  },
  {
    "id": 58920,
    "uid": "poem-17-29",
    "chapter": "卷十七",
    "chapternum": 17,
    "charstyle": "古體詩",
    "title": "終南幽居獻蘓侍郎〈時拜太祝未上〉",
    "titledesc": "",
    "collection": "",
    "collectiondesc": "",
    "poemindex": 29,
    "author": "儲光羲",
    "content": "中嵗尚㣲道始知將谷神抗䇿還南山水木自相親深林門一道青嶂成四鄰平明去採薇日入行刈薪雲歸萬壑暗雪罷千巖春始看玄鳥來已見瑤華新寄言搴芳者無乃後時人"
  },
  {
    "id": 58924,
    "uid": "poem-17-33",
    "chapter": "卷十七",
    "chapternum": 17,
    "charstyle": "古體詩",
    "title": "同王十三維偶然作",
    "titledesc": "",
    "collection": "",
    "collectiondesc": "",
    "poemindex": 33,
    "author": "儲光羲",
    "content": "北山種松栢南山種蒺藜出入雖同趣所尚各有宜孔丘貴仁義老氏好無為我心若虚空此道將安施暫過伊闕間晼晩三伏時高閣入雲中芙蓉滿清池要自非我室還望南山陲"
  },
  {
    "id": 58933,
    "uid": "poem-17-42",
    "chapter": "卷十七",
    "chapternum": 17,
    "charstyle": "古體詩",
    "title": "田家雜興",
    "titledesc": "",
    "collection": "",
    "collectiondesc": "",
    "poemindex": 42,
    "author": "儲光羲",
    "content": "田家趣隴畆當晝掩虚闗鄰里無煙火兒童共幽閒桔橰懸空圃雞犬滿桑間須㬰農事隙採藥遊名山但願所采多不言路險艱人生如蜉蝣一往不可攀君看西王母千嵗美容顔"
  },
  {
    "id": 58934,
    "uid": "poem-17-43",
    "chapter": "卷十七",
    "chapternum": 17,
    "charstyle": "古體詩",
    "title": "田家雜興",
    "titledesc": "",
    "collection": "",
    "collectiondesc": "",
    "poemindex": 43,
    "author": "儲光羲",
    "content": "貧士養情性不復知憂樂去年行賣畚留滯南陽郭秋至黍苗黄無人可刈穫孺子朝來飯把竿逐鳥雀忽見梁將軍乗車出宛洛意氣軼道路光輝滿墟落安知負薪者咥咥笑輕薄"
  },
  {
    "id": 58997,
    "uid": "poem-17-106",
    "chapter": "卷十七",
    "chapternum": 17,
    "charstyle": "古體詩",
    "title": "采蓮曲",
    "titledesc": "",
    "collection": "",
    "collectiondesc": "",
    "poemindex": 106,
    "author": "李康成",
    "content": "采蓮去月没春江曙翠鈿紅袖水中央青荷蓮子雜衣香雲起風生歸路長歸路長那得久各迴船兩搖手"
  }
]